docembedder/__init__.py
docembedder/_version.py
docembedder/analysis.py
docembedder/classification.py
docembedder/datamodel.py
docembedder/embedding_utils.py
docembedder/pretrained_run.py
docembedder/simspec.py
docembedder/typing.py
docembedder/utils.py
docembedder/visualization.py
docembedder/hyperopt/__init__.py
docembedder/hyperopt/parallel.py
docembedder/hyperopt/utils.py
docembedder/models/__init__.py
docembedder/models/base.py
docembedder/models/bert.py
docembedder/models/bpemb.py
docembedder/models/countvec.py
docembedder/models/doc2vec.py
docembedder/models/tfidf.py
docembedder/models/utils.py
docembedder/preprocessor/__init__.py
docembedder/preprocessor/oldprep.py
docembedder/preprocessor/parser.py
docembedder/preprocessor/preprocessor.py
docembedder-0.1.0.dist-info/LICENSE
docembedder-0.1.0.dist-info/METADATA
docembedder-0.1.0.dist-info/WHEEL
docembedder-0.1.0.dist-info/top_level.txt
docembedder-0.1.0.dist-info/RECORD
