Metadata-Version: 2.1
Name: docembedder
Version: 0.1.0
Summary: Package for creating document embeddings of patents and analysis tools.
Author-email: Raoul Schram <r.d.schram@uu.nl>, Shiva Nadi <s.nadinajafabadi@uu.nl>, Maarten Schermer <m.d.schermer@uu.nl>, Jelle Treep <h.j.treep@uu.nl>
License: MIT License
Project-URL: GitHub, https://github.com/UtrechtUniversity/patent-breakthrough
Project-URL: documentation, https://github.com/UtrechtUniversity/patent-breakthrough/tree/main/docs
Keywords: patents,embeddings,machine learning
Classifier: Programming Language :: Python :: 3
Classifier: Programming Language :: Python :: 3.8
Classifier: Programming Language :: Python :: 3.9
Classifier: Programming Language :: Python :: 3.10
Classifier: Programming Language :: Python :: 3.11
Classifier: Development Status :: 3 - Alpha
Classifier: License :: OSI Approved :: MIT License
Requires-Python: >=3.8
License-File: LICENSE
Requires-Dist: numpy
Requires-Dist: scipy
Requires-Dist: scikit-learn
Requires-Dist: torch
Requires-Dist: torchvision
Requires-Dist: transformers
Requires-Dist: sentence-transformers
Requires-Dist: pandas
Requires-Dist: dill
Requires-Dist: nltk
Requires-Dist: gensim
Requires-Dist: bpemb
Requires-Dist: polars >=0.16
Requires-Dist: pyarrow
Requires-Dist: matplotlib
Requires-Dist: tqdm
Requires-Dist: h5py
Requires-Dist: hyperopt
